pysdvb
