Metadata-Version: 1.1
Name: py-sdvb
Version: 2.1
Summary: Dictionary interface of stardict, support regular expression (regex) search and colored output.
Home-page: https://github.com/noinil/py_sdvb
Author: Cheng Tan
Author-email: noinil@gmail.com
License: GPL3
Download-URL: https://github.com/noinil/py_sdvb/archive/v2.1.zip
Keywords: dictionary,stardict,vocabulary builder,English,Chinese
Platform: UNKNOWN
Classifier: Programming Language :: Python :: 3
Classifier: Programming Language :: Python :: 3.5
